testasddsa/main.py
testasddsa-0.1.0.dist-info/METADATA
testasddsa-0.1.0.dist-info/WHEEL
testasddsa-0.1.0.dist-info/RECORD
