Metadata-Version: 2.1
Name: testasddsa
Version: 0.1.0
Summary: DEMO pipeline
Author: Borislav Nachev
Author-email: 220472@buas.nl
Requires-Python: ==3.10.14
Classifier: Programming Language :: Python :: 3
Requires-Dist: coverage (>=7.5.1,<8.0.0)
Requires-Dist: matplotlib (>=3.8.4,<4.0.0)
Requires-Dist: networkx (>=3.3,<4.0)
Requires-Dist: numpy (==1.23.5)
Requires-Dist: opencv-python (>=4.9.0.80,<5.0.0.0)
Requires-Dist: pandas (>=2.2.2,<3.0.0)
Requires-Dist: patchify (>=0.2.3,<0.3.0)
Requires-Dist: pytest (>=8.2.0,<9.0.0)
Requires-Dist: pytest-mock (>=3.14.0,<4.0.0)
Requires-Dist: scikit-image (>=0.23.2,<0.24.0)
Requires-Dist: skan (>=0.11.1,<0.12.0)
Requires-Dist: sphinx (>=7.3.7,<8.0.0)
Requires-Dist: tensorflow (==2.10.0)
Requires-Dist: tensorflow-io-gcs-filesystem (==0.30.0)
